Workbook

Sheet Cuentas & Servicios
A1: Servicio | B1: Tipo | C1: Uso en FiltroLlamadas | D1: Modelo de Cobro | E1: Costo Base (USD/mes) | F1: Variable | G1: Credenciales / Env Var | H1: URL Consola | I1: Estado
A2: Twilio | B2: Telefonía + WhatsApp | C2: Voz entrante, TTS Polly, WhatsApp msgs | D2: Pay-per-use | E2: 0 | F2: ~$0.02/min voz + $0.005/msg WA + $1.15/num | G2: TWILIO_ACCOUNT_SID, TWILIO_AUTH_TOKEN, TWILIO_WHATSAPP_NUMBER | H2: https://console.twilio.com | I2: Activo
A3: OpenAI | B3: LLM (GPT-4o-mini) | C3: Conversación IA + análisis post-llamada | D3: Pay-per-token | E3: 0 | F3: $0.15/1M input + $0.60/1M output tokens | G3: OPENAI_API_KEY | H3: https://platform.openai.com | I3: Activo
A4: ElevenLabs | B4: TTS Premium | C4: Voces ultra-realistas (Pro/Premium) | D4: Suscripción + uso | E4: 5 | F4: $5/mes Starter (30K chars) o $0.18/1K chars | G4: ELEVENLABS_API_KEY, ELEVENLABS_VOICE_ID | H4: https://elevenlabs.io | I4: Activo
A5: Railway | B5: Hosting Backend | C5: FastAPI + PostgreSQL en producción | D5: Suscripción + uso | E5: 5 | F5: $5/mes Hobby (incluye $5 crédito uso) | G5: DATABASE_URL, BASE_URL | H5: https://railway.app/dashboard | I5: Activo
A6: Railway PostgreSQL | B6: Base de Datos | C6: Incluido en Railway (mismo proyecto) | D6: Incluido | E6: 0 | F6: Incluido en los $5 de Railway | G6: DATABASE_URL | H6: https://railway.app/dashboard | I6: Activo
A7: Google Cloud | B7: OAuth2 Calendar API | C7: Integración Google Calendar (Pro) | D7: Gratis | E7: 0 | F7: Gratis hasta millones de requests | G7: GOOGLE_CLIENT_ID, GOOGLE_CLIENT_SECRET | H7: https://console.cloud.google.com | I7: Activo
A8: Microsoft Azure AD | B8: OAuth2 Calendar API | C8: Integración Outlook Calendar (Pro) | D8: Gratis | E8: 0 | F8: Gratis tier básico | G8: OUTLOOK_CLIENT_ID, OUTLOOK_CLIENT_SECRET | H8: https://portal.azure.com | I8: Pendiente
A9: Apple Developer | B9: App Store | C9: Publicación iOS + In-App Purchases | D9: Anual | E9: 8.25 | F9: $99/año = $8.25/mes | G9: Apple Developer Account | H9: https://developer.apple.com | I9: Pendiente
A10: Apple App Store | B10: Comisión ventas | C10: 15% de cada suscripción (Small Business) | D10: % ventas | E10: 0 | F10: 15% de revenue (< $1M USD/año) | G10: N/A | H10: https://appstoreconnect.apple.com | I10: Pendiente
A11: GitHub | B11: Repositorio | C11: Código fuente del proyecto | D11: Gratis | E11: 0 | F11: Gratis (repo privado) | G11: N/A | H11: https://github.com | I11: Activo
A12: RevenueCat (recomendado) | B12: Gestión suscripciones | C12: Manejo IAP Apple/Google, analytics | D12: Gratis hasta $2.5K | E12: 0 | F12: Gratis < $2,500 MRR, luego 1% | G12: N/A | H12: https://revenuecat.com | I12: Pendiente
A13: TOTAL COSTO BASE MENSUAL | E13: =SUM(E2:E12) -> 18.25
A14: MercadoPago | B14: Pagos Web | C14: Suscripciones Pro/Premium vía web | D14: Comisión | E14: 0 | F14: ~3.49% + IVA por transacción | G14: MERCADOPAGO_ACCESS_TOKEN | H14: https://mercadopago.cl/developers | I14: Pendiente
A15: Dominio (.cl/.com) | B15: DNS + Identidad | C15: filtrollamadas.cl para web y emails | D15: Anual | E15: 0.83 | F15: $10 USD/año = $0.83/mes | G15: — | H15: https://nic.cl | I15: Pendiente
A16: Google Workspace | B16: Email corporativo | C16: soporte@filtrollamadas.cl | D16: Suscripción | E16: 7 | F16: $7/mes Business Starter 1 usuario | G16: — | H16: https://workspace.google.com | I16: Opcional
A17: SPA (Sociedad) | B17: Legal | C17: RUT empresa, facturación, cta bancaria | D17: Único | E17: 0 | F17: $0 online en registrodeempresas.cl | G17: — | H17: https://registrodeempresas.cl | I17: Pendiente
A18: Contador | B18: Contabilidad | C18: IVA, renta, boletas | D18: Mensual | E18: 30 | F18: $20-40 USD/mes freelance Chile | G18: — | H18: — | I18: Pendiente

Sheet Base de Datos
A1: CRECIMIENTO DE BASE DE DATOS
A3: TAMAÑO POR REGISTRO
A4: Tabla | B4: Campos principales | C4: Bytes/registro | D4: Registros/usuario/mes | E4: MB/usuario/mes | F4: Notas
A5: usuarios | B5: uid, nombre, email, config, tokens JSON | C5: 2048 | D5: 0 | E5: =IF(D5>0,C5*D5/1048576,0) -> 0 | F5: Solo 1 registro por usuario
A6: llamadas | B6: call_sid, transcripcion, resumen, etc | C6: 4096 | D6: 15 | E6: =IF(D6>0,C6*D6/1048576,0) -> 0.05859375 | F6: 15 llamadas/mes promedio
A7: suscripciones | B7: plan, pago, estado, fechas | C7: 512 | D7: 1 | E7: =IF(D7>0,C7*D7/1048576,0) -> 0.00048828125 | F7: 1 registro por periodo
A8: numeros_bloqueados | B8: numero, razon | C8: 128 | D8: 2 | E8: =IF(D8>0,C8*D8/1048576,0) -> 0.00024414062 | F8: ~2 bloqueados acumulado
A9: audio (disco) | B9: MP3 saludos + TTS cache | C9: 300000 | D9: 1 | E9: =IF(D9>0,C9*D9/1048576,0) -> 0.28610229 | F9: ~300KB promedio, no en DB
A10: TOTAL por usuario/mes | E10: =SUM(E5:E9) -> 0.34542847 | F10: MB en PostgreSQL + disco
A12: PROYECCIÓN ALMACENAMIENTO 12 MESES
A13: MB/usuario/mes (DB+disco) | B13: =E10 -> 0.34542847
A14: Railway Hobby incluye | B14: 1 GB PostgreSQL + 1 GB disco
B16: Mes 1 | C16: Mes 2 | D16: Mes 3 | E16: Mes 4 | F16: Mes 5 | G16: Mes 6 | H16: Mes 7 | I16: Mes 8 | J16: Mes 9 | K16: Mes 10 | L16: Mes 11 | M16: Mes 12
A17: Total Usuarios | B17: ='Proyección 12 Meses'!B7 -> 112 | C17: ='Proyección 12 Meses'!C7 -> 122 | D17: ='Proyección 12 Meses'!D7 -> 133 | E17: ='Proyección 12 Meses'!E7 -> 143 | F17: ='Proyección 12 Meses'!F7 -> 153 | G17: ='Proyección 12 Meses'!G7 -> 164 | H17: ='Proyección 12 Meses'!H7 -> 174 | I17: ='Proyección 12 Meses'!I7 -> 185 | ... M17: ='Proyección 12 Meses'!M7 -> 231
A18: DB acumulada (MB) | B18: =B17*$B$13 -> 38.687988 | C18: =B18+C17*$B$13 -> 80.830261 | D18: =C18+D17*$B$13 -> 126.77225 | E18: =D18+E17*$B$13 -> 176.16852 | F18: =E18+F17*$B$13 -> 229.01907 | G18: =F18+G17*$B$13 -> 285.66934 | H18: =G18+H17*$B$13 -> 345.7739 | I18: =H18+I17*$B$13 -> 409.67816 | J18: =I18+J17*$B$13 -> 477.38214 | ... M18: =L18+M17*$B$13 -> 704.32864
A19: % de 1 GB usado | B19: =B18/1024 -> 0.037781239 | C19: =C18/1024 -> 0.078935802 | D19: =D18/1024 -> 0.12380102 | E19: =E18/1024 -> 0.17203957 | F19: =F18/1024 -> 0.22365144 | G19: =G18/1024 -> 0.27897397 | H19: =H18/1024 -> 0.33766982 | I19: =I18/1024 -> 0.40007633 | ... M19: =M18/1024 -> 0.68782094
A20: ¿Necesita upgrade? | B20: =IF(B19>0.7,"UPGRADE!","OK") -> OK | C20: =IF(C19>0.7,"UPGRADE!","OK") -> OK | D20: =IF(D19>0.7,"UPGRADE!","OK") -> OK | E20: =IF(E19>0.7,"UPGRADE!","OK") -> OK | F20: =IF(F19>0.7,"UPGRADE!","OK") -> OK | G20: =IF(G19>0.7,"UPGRADE!","OK") -> OK | H20: =IF(H19>0.7,"UPGRADE!","OK") -> OK | I20: =IF(I19>0.7,"UPGRADE!","OK") -> OK | ... M20: =IF(M19>0.7,"UPGRADE!","OK") -> OK
A22: PLANES RAILWAY
A23: Plan | B23: Precio | C23: PostgreSQL | D23: Usuarios aprox
A24: Hobby | B24: $5/mes | C24: 1 GB | D24: ~200-400
A25: Pro | B25: $20/mes | C25: 10 GB | D25: ~2,000-5,000
A26: Enterprise | B26: Custom | C26: Ilimitado | D26: 5,000+
A28: ESTRATEGIAS DE CONTROL
A29: 1. Limpiar audio_cache cada 7 días
A30: 2. Archivar llamadas > 90 días
A31: 3. Upgrade Railway a Pro cuando DB > 700MB
A32: 4. Limitar audio saludo a 30 seg (~250KB)

Sheet Costos Operacionales
A1: COSTOS OPERACIONALES COMPLETOS
A3: COSTOS ÚNICOS (Pre-lanzamiento)
A4: Concepto | B4: USD | C4: CLP (aprox) | D4: Notas
A5: SPA Registro de Empresas | B5: 0 | C5: =B5*950 -> 0 | D5: Gratis online
A6: Apple Developer Program | B6: 99 | C6: =B6*950 -> 94050 | D6: $99 USD/año
A7: Dominio filtrollamadas.cl | B7: 10 | C7: =B7*950 -> 9500 | D7: $10 USD/año NIC Chile
A8: Notaría/poderes | B8: 20 | C8: =B8*950 -> 19000 | D8: Estimado
A9: Cuenta bancaria empresa | B9: 0 | C9: =B9*950 -> 0 | D9: Gratis
A10: Registro MercadoPago | B10: 0 | C10: =B10*950 -> 0 | D10: Gratis
A11: TOTAL PRE-LANZAMIENTO | B11: =SUM(B5:B10) -> 129 | C11: =B11*950 -> 122550
A13: COSTOS FIJOS MENSUALES
A14: Concepto | B14: USD/mes | C14: CLP/mes | D14: Notas
A15: Railway Hobby (hosting + DB) | B15: 5 | C15: =B15*950 -> 4750 | D15: Incluye 1GB PostgreSQL
A16: ElevenLabs Starter | B16: 5 | C16: =B16*950 -> 4750 | D16: 30K chars/mes voces premium
A17: Apple Developer (÷12) | B17: 8.25 | C17: =B17*950 -> 7837.5 | D17: $99/año prorrateado
A18: Contador freelance | B18: 30 | C18: =B18*950 -> 28500 | D18: IVA, renta, boletas
A19: Dominio (÷12) | B19: 0.83 | C19: =B19*950 -> 788.5 | D19: $10/año prorrateado
A20: Twilio número | B20: 1.15 | C20: =B20*950 -> 1092.5 | D20: $1.15/mes por número
A21: Google Workspace (OPCIONAL) | B21: 7 | C21: =B21*950 -> 6650 | D21: Email corporativo
A22: TOTAL sin Google Workspace | B22: =SUM(B15:B20) -> 50.23 | C22: =B22*950 -> 47718.5
A23: TOTAL con Google Workspace | B23: =SUM(B15:B21) -> 57.23 | C23: =B23*950 -> 54368.5
A25: COMPARACIÓN PROCESADORES DE PAGO
A26: Canal | B26: Comisión | C26: Neto de $4.99 | D26: Neto de $12.99
A27: MercadoPago (web) | B27: ~4.16% | C27: =4.99*(1-0.0416) -> 4.782416 | D27: =9.99*(1-0.0416) -> 9.574416
A28: Apple IAP 15% | B28: 15% | C28: =4.99*0.85 -> 4.2415 | D28: =9.99*0.85 -> 8.4915
A29: Apple IAP 30% | B29: 30% | C29: =4.99*0.7 -> 3.493 | D29: =9.99*0.7 -> 6.993
A30: Google Play 15% | B30: 15% | C30: =4.99*0.85 -> 4.2415 | D30: =9.99*0.85 -> 8.4915
A31: Stripe (web) | B31: 3.25% | C31: =4.99*(1-0.0325) -> 4.827825 | D31: =9.99*(1-0.0325) -> 9.665325
A34: ROADMAP RECOMENDADO
A35: Etapa | B35: Acción | C35: Costo
A36: Ahora (0 usuarios) | B36: Correo personal, sin SPA. Solo desarrollar | C36: $0
A37: Primeros 10 pagando | B37: Crear SPA + MercadoPago empresa | C37: ~$20 único
A38: 50+ usuarios | B38: Dominio + Google Workspace | C38: ~$18/mes
A39: 100+ usuarios | B39: Apple Developer + App Store | C39: $99/año
A40: 500+ usuarios | B40: Railway Pro ($20/mes) | C40: $20/mes
A41: 1000+ usuarios | B41: Migrar a AWS/GCP | C41: Variable

Sheet Modelo Financiero
A1: SUPUESTOS DEL MODELO
A3: Supuestos de Usuarios
A4: Usuarios Free | B4: 100 | C4: Supuesto mes 1
A5: Usuarios Pro ($4.99/mes) | B5: 10 | C5: Supuesto mes 1
A6: Usuarios Premium ($12.99/mes) | B6: 2 | C6: Supuesto mes 1
A7: Crecimiento mensual usuarios | B7: 0.15 | C7: 15% mes a mes
A8: Conversión Free → Pro | B8: 0.08 | C8: 8% de free se convierten
A9: Conversión Pro → Premium | B9: 0.05 | C9: 5% de pro suben
A10: Churn mensual | B10: 0.04 | C10: 4% se van cada mes
A12: Supuestos de Uso por Usuario/Mes
A13: Llamadas promedio (Free) | B13: 15 | C13: de 30 max
A14: Llamadas promedio (Pro) | B14: 50 | C14: de 200 max
A15: Llamadas promedio (Premium) | B15: 80 | C15: ilimitado
A16: Duración promedio llamada (min) | B16: 2.5
A17: Tokens input promedio/llamada | B17: 800 | C17: prompt + conversación
A18: Tokens output promedio/llamada | B18: 200 | C18: respuesta IA
A19: Chars TTS ElevenLabs/llamada | B19: 150 | C19: solo Pro/Premium
A20: WhatsApp msgs/llamada | B20: 2 | C20: alerta + resumen
A22: Costos Unitarios
A23: Twilio: voz recibir (USD/min) | B23: 0.0085 | C23: Source: twilio.com/voice/pricing
A24: Twilio: voz hacer (USD/min) | B24: 0.014 | C24: Source: twilio.com/voice/pricing
A25: Twilio: WhatsApp (USD/msg) | B25: 0.005 | C25: Source: twilio.com/whatsapp/pricing
A26: Twilio: número teléfono (USD/mes) | B26: 1.15 | C26: Source: twilio.com/pricing
A27: OpenAI: input (USD/1M tokens) | B27: 0.15 | C27: Source: openai.com/api/pricing
A28: OpenAI: output (USD/1M tokens) | B28: 0.6 | C28: Source: openai.com/api/pricing
A29: ElevenLabs: suscripción (USD/mes) | B29: 5 | C29: Starter plan
A30: Railway: hosting (USD/mes) | B30: 5 | C30: Hobby plan
A31: Apple Developer (USD/mes) | B31: 8.25 | C31: $99/año prorrateado
A32: Apple comisión (%) | B32: 0.15 | C32: Small Business Program

Sheet Proyección 12 Meses
A1: PROYECCIÓN FINANCIERA 12 MESES
B2: Mes 1 | C2: Mes 2 | D2: Mes 3 | E2: Mes 4 | F2: Mes 5 | G2: Mes 6 | H2: Mes 7 | I2: Mes 8 | J2: Mes 9 | K2: Mes 10 | L2: Mes 11 | M2: Mes 12 | N2: TOTAL AÑO
A3: USUARIOS
A4: Usuarios Free | B4: ='Modelo Financiero'!B4 -> 100 | C4: =ROUND(B4*(1+'Modelo Financiero'!B7)-B4*'Modelo Financiero'!B8-B4*'Modelo Financiero'!B10,0) -> 103 | D4: =ROUND(C4*(1+'Modelo Financiero'!B7)-C4*'Modelo Financiero'!B8-C4*'Modelo Financiero'!B10,0) -> 106 | E4: =ROUND(D4*(1+'Modelo Financiero'!B7)-D4*'Modelo Financiero'!B8-D4*'Modelo Financiero'!B10,0) -> 109 | F4: =ROUND(E4*(1+'Modelo Financiero'!B7)-E4*'Modelo Financiero'!B8-E4*'Modelo Financiero'!B10,0) -> 112 | G4: =ROUND(F4*(1+'Modelo Financiero'!B7)-F4*'Modelo Financiero'!B8-F4*'Modelo Financiero'!B10,0) -> 115 | H4: =ROUND(G4*(1+'Modelo Financiero'!B7)-G4*'Modelo Financiero'!B8-G4*'Modelo Financiero'!B10,0) -> 118 | I4: =ROUND(H4*(1+'Modelo Financiero'!B7)-H4*'Modelo Financiero'!B8-H4*'Modelo Financiero'!B10,0) -> 122 | J4: =ROUND(I4*(1+'Modelo Financiero'!B7)-I4*'Modelo Financiero'!B8-I4*'Modelo Financiero'!B10,0) -> 126 | K4: =ROUND(J4*(1+'Modelo Financiero'!B7)-J4*'Modelo Financiero'!B8-J4*'Modelo Financiero'!B10,0) -> 130 | L4: =ROUND(K4*(1+'Modelo Financiero'!B7)-K4*'Modelo Financiero'!B8-K4*'Modelo Financiero'!B10,0) -> 134 | M4: =ROUND(L4*(1+'Modelo Financiero'!B7)-L4*'Modelo Financiero'!B8-L4*'Modelo Financiero'!B10,0) -> 138 | N4: =M4 -> 138
A5: Usuarios Pro | B5: ='Modelo Financiero'!B5 -> 10 | C5: =ROUND(B5+B4*'Modelo Financiero'!B8-B5*'Modelo Financiero'!B9-B5*'Modelo Financiero'!B10,0) -> 17 | D5: =ROUND(C5+C4*'Modelo Financiero'!B8-C5*'Modelo Financiero'!B9-C5*'Modelo Financiero'!B10,0) -> 24 | E5: =ROUND(D5+D4*'Modelo Financiero'!B8-D5*'Modelo Financiero'!B9-D5*'Modelo Financiero'!B10,0) -> 30 | F5: =ROUND(E5+E4*'Modelo Financiero'!B8-E5*'Modelo Financiero'!B9-E5*'Modelo Financiero'!B10,0) -> 36 | G5: =ROUND(F5+F4*'Modelo Financiero'!B8-F5*'Modelo Financiero'!B9-F5*'Modelo Financiero'!B10,0) -> 42 | H5: =ROUND(G5+G4*'Modelo Financiero'!B8-G5*'Modelo Financiero'!B9-G5*'Modelo Financiero'!B10,0) -> 47 | I5: =ROUND(H5+H4*'Modelo Financiero'!B8-H5*'Modelo Financiero'!B9-H5*'Modelo Financiero'!B10,0) -> 52 | J5: =ROUND(I5+I4*'Modelo Financiero'!B8-I5*'Modelo Financiero'!B9-I5*'Modelo Financiero'!B10,0) -> 57 | K5: =ROUND(J5+J4*'Modelo Financiero'!B8-J5*'Modelo Financiero'!B9-J5*'Modelo Financiero'!B10,0) -> 62 | L5: =ROUND(K5+K4*'Modelo Financiero'!B8-K5*'Modelo Financiero'!B9-K5*'Modelo Financiero'!B10,0) -> 67 | M5: =ROUND(L5+L4*'Modelo Financiero'!B8-L5*'Modelo Financiero'!B9-L5*'Modelo Financiero'!B10,0) -> 72 | N5: =M5 -> 72
A6: Usuarios Premium | B6: ='Modelo Financiero'!B6 -> 2 | C6: =ROUND(B6+B5*'Modelo Financiero'!B9-B6*'Modelo Financiero'!B10,0) -> 2 | D6: =ROUND(C6+C5*'Modelo Financiero'!B9-C6*'Modelo Financiero'!B10,0) -> 3 | E6: =ROUND(D6+D5*'Modelo Financiero'!B9-D6*'Modelo Financiero'!B10,0) -> 4 | F6: =ROUND(E6+E5*'Modelo Financiero'!B9-E6*'Modelo Financiero'!B10,0) -> 5 | G6: =ROUND(F6+F5*'Modelo Financiero'!B9-F6*'Modelo Financiero'!B10,0) -> 7 | H6: =ROUND(G6+G5*'Modelo Financiero'!B9-G6*'Modelo Financiero'!B10,0) -> 9 | I6: =ROUND(H6+H5*'Modelo Financiero'!B9-H6*'Modelo Financiero'!B10,0) -> 11 | J6: =ROUND(I6+I5*'Modelo Financiero'!B9-I6*'Modelo Financiero'!B10,0) -> 13 | K6: =ROUND(J6+J5*'Modelo Financiero'!B9-J6*'Modelo Financiero'!B10,0) -> 15 | L6: =ROUND(K6+K5*'Modelo Financiero'!B9-K6*'Modelo Financiero'!B10,0) -> 18 | M6: =ROUND(L6+L5*'Modelo Financiero'!B9-L6*'Modelo Financiero'!B10,0) -> 21 | N6: =M6 -> 21
A7: Total Usuarios | B7: =B4+B5+B6 -> 112 | C7: =C4+C5+C6 -> 122 | D7: =D4+D5+D6 -> 133 | E7: =E4+E5+E6 -> 143 | F7: =F4+F5+F6 -> 153 | G7: =G4+G5+G6 -> 164 | H7: =H4+H5+H6 -> 174 | I7: =I4+I5+I6 -> 185 | ... M7: =M4+M5+M6 -> 231 | N7: =M7 -> 231
A9: REVENUE (antes de Apple)
A10: Revenue Pro (bruto) | B10: =B5*4.99 -> 49.9 | C10: =C5*4.99 -> 84.83 | D10: =D5*4.99 -> 119.76 | E10: =E5*4.99 -> 149.7 | F10: =F5*4.99 -> 179.64 | G10: =G5*4.99 -> 209.58 | H10: =H5*4.99 -> 234.53 | I10: =I5*4.99 -> 259.48 | ... M10: =M5*4.99 -> 359.28 | N10: =SUM(B10:M10) -> 2574.84
A11: Revenue Premium (bruto) | B11: =B6*9.99 -> 19.98 | C11: =C6*9.99 -> 19.98 | D11: =D6*9.99 -> 29.97 | E11: =E6*9.99 -> 39.96 | F11: =F6*9.99 -> 49.95 | G11: =G6*9.99 -> 69.93 | H11: =H6*9.99 -> 89.91 | I11: =I6*9.99 -> 109.89 | ... N11: =N6*9.99 -> 209.79
A12: Revenue Bruto Total | B12: =B10+B11 -> 69.88 | C12: =C10+C11 -> 104.81 | D12: =D10+D11 -> 149.73 | E12: =E10+E11 -> 189.66 | F12: =F10+F11 -> 229.59 | G12: =G10+G11 -> 279.51 | H12: =H10+H11 -> 324.44 | I12: =I10+I11 -> 369.37 | ... M12: =M10+M11 -> 569.07 | N12: =SUM(B12:M12) -> 3673.74
A13: Comisión Apple (15%) | B13: =B12*'Modelo Financiero'!B32 -> 10.482 | C13: =C12*'Modelo Financiero'!B32 -> 15.7215 | D13: =D12*'Modelo Financiero'!B32 -> 22.4595 | E13: =E12*'Modelo Financiero'!B32 -> 28.449 | F13: =F12*'Modelo Financiero'!B32 -> 34.4385 | G13: =G12*'Modelo Financiero'!B32 -> 41.9265 | H13: =H12*'Modelo Financiero'!B32 -> 48.666 | I13: =I12*'Modelo Financiero'!B32 -> 55.4055 | J13: =J12*'Modelo Financiero'!B32 -> 62.145 | K13: =K12*'Modelo Financiero'!B32 -> 68.8845 | L13: =L12*'Modelo Financiero'!B32 -> 77.1225 | M13: =M12*'Modelo Financiero'!B32 -> 85.3605 | N13: =SUM(B13:M13) -> 551.061
A14: Revenue Neto | B14: =B12-B13 -> 59.398 | C14: =C12-C13 -> 89.0885 | D14: =D12-D13 -> 127.2705 | E14: =E12-E13 -> 161.211 | F14: =F12-F13 -> 195.1515 | G14: =G12-G13 -> 237.5835 | H14: =H12-H13 -> 275.774 | I14: =I12-I13 -> 313.9645 | ... M14: =M12-M13 -> 483.7095 | N14: =SUM(B14:M14) -> 3122.679
A16: COSTOS VARIABLES
A17: Twilio: Voz (llamadas) | B17: =(B4*'Modelo Financiero'!B13+B5*'Modelo Financiero'!B14+B6*'Modelo Financiero'!B15)*'Modelo Financiero'!B16*'Modelo Financiero'!B23 -> 45.9 | C17: =(C4*'Modelo Financiero'!B13+C5*'Modelo Financiero'!B14+C6*'Modelo Financiero'!B15)*'Modelo Financiero'!B16*'Modelo Financiero'!B23 -> 54.29375 | D17: =(D4*'Modelo Financiero'!B13+D5*'Modelo Financiero'!B14+D6*'Modelo Financiero'!B15)*'Modelo Financiero'!B16*'Modelo Financiero'!B23 -> 64.3875 | E17: =(E4*'Modelo Financiero'!B13+E5*'Modelo Financiero'!B14+E6*'Modelo Financiero'!B15)*'Modelo Financiero'!B16*'Modelo Financiero'!B23 -> 73.41875 | F17: =(F4*'Modelo Financiero'!B13+F5*'Modelo Financiero'!B14+F6*'Modelo Financiero'!B15)*'Modelo Financiero'!B16*'Modelo Financiero'!B23 -> 82.45 | G17: =(G4*'Modelo Financiero'!B13+G5*'Modelo Financiero'!B14+G6*'Modelo Financiero'!B15)*'Modelo Financiero'!B16*'Modelo Financiero'!B23 -> 93.18125 | H17: =(H4*'Modelo Financiero'!B13+H5*'Modelo Financiero'!B14+H6*'Modelo Financiero'!B15)*'Modelo Financiero'!B16*'Modelo Financiero'!B23 -> 102.85 | I17: =(I4*'Modelo Financiero'!B13+I5*'Modelo Financiero'!B14+I6*'Modelo Financiero'!B15)*'Modelo Financiero'!B16*'Modelo Financiero'!B23 -> 112.8375 | J17: =(J4*'Modelo Financiero'!B13+J5*'Modelo Financiero'!B14+J6*'Modelo Financiero'!B15)*'Modelo Financiero'!B16*'Modelo Financiero'!B23 -> 122.825 | K17: =(K4*'Modelo Financiero'!B13+K5*'Modelo Financiero'!B14+K6*'Modelo Financiero'!B15)*'Modelo Financiero'!B16*'Modelo Financiero'!B23 -> 132.8125 | L17: =(L4*'Modelo Financiero'!B13+L5*'Modelo Financiero'!B14+L6*'Modelo Financiero'!B15)*'Modelo Financiero'!B16*'Modelo Financiero'!B23 -> 144.5 | M17: =(M4*'Modelo Financiero'!B13+M5*'Modelo Financiero'!B14+M6*'Modelo Financiero'!B15)*'Modelo Financiero'!B16*'Modelo Financiero'!B23 -> 156.1875 | N17: =SUM(B17:M17) -> 1185.6438
A18: Twilio: WhatsApp | B18: =(B4*'Modelo Financiero'!B13+B5*'Modelo Financiero'!B14+B6*'Modelo Financiero'!B15)*'Modelo Financiero'!B20*'Modelo Financiero'!B25 -> 21.6 | C18: =(C4*'Modelo Financiero'!B13+C5*'Modelo Financiero'!B14+C6*'Modelo Financiero'!B15)*'Modelo Financiero'!B20*'Modelo Financiero'!B25 -> 25.55 | D18: =(D4*'Modelo Financiero'!B13+D5*'Modelo Financiero'!B14+D6*'Modelo Financiero'!B15)*'Modelo Financiero'!B20*'Modelo Financiero'!B25 -> 30.3 | E18: =(E4*'Modelo Financiero'!B13+E5*'Modelo Financiero'!B14+E6*'Modelo Financiero'!B15)*'Modelo Financiero'!B20*'Modelo Financiero'!B25 -> 34.55 | F18: =(F4*'Modelo Financiero'!B13+F5*'Modelo Financiero'!B14+F6*'Modelo Financiero'!B15)*'Modelo Financiero'!B20*'Modelo Financiero'!B25 -> 38.8 | G18: =(G4*'Modelo Financiero'!B13+G5*'Modelo Financiero'!B14+G6*'Modelo Financiero'!B15)*'Modelo Financiero'!B20*'Modelo Financiero'!B25 -> 43.85 | H18: =(H4*'Modelo Financiero'!B13+H5*'Modelo Financiero'!B14+H6*'Modelo Financiero'!B15)*'Modelo Financiero'!B20*'Modelo Financiero'!B25 -> 48.4 | I18: =(I4*'Modelo Financiero'!B13+I5*'Modelo Financiero'!B14+I6*'Modelo Financiero'!B15)*'Modelo Financiero'!B20*'Modelo Financiero'!B25 -> 53.1 | J18: =(J4*'Modelo Financiero'!B13+J5*'Modelo Financiero'!B14+J6*'Modelo Financiero'!B15)*'Modelo Financiero'!B20*'Modelo Financiero'!B25 -> 57.8 | K18: =(K4*'Modelo Financiero'!B13+K5*'Modelo Financiero'!B14+K6*'Modelo Financiero'!B15)*'Modelo Financiero'!B20*'Modelo Financiero'!B25 -> 62.5 | L18: =(L4*'Modelo Financiero'!B13+L5*'Modelo Financiero'!B14+L6*'Modelo Financiero'!B15)*'Modelo Financiero'!B20*'Modelo Financiero'!B25 -> 68 | M18: =(M4*'Modelo Financiero'!B13+M5*'Modelo Financiero'!B14+M6*'Modelo Financiero'!B15)*'Modelo Financiero'!B20*'Modelo Financiero'!B25 -> 73.5 | N18: =SUM(B18:M18) -> 557.95
A19: Twilio: Números telefónicos | B19: ='Modelo Financiero'!$B$26*B7 -> 128.8 | C19: ='Modelo Financiero'!$B$26*C7 -> 140.3 | D19: ='Modelo Financiero'!$B$26*D7 -> 152.95 | E19: ='Modelo Financiero'!$B$26*E7 -> 164.45 | F19: ='Modelo Financiero'!$B$26*F7 -> 175.95 | G19: ='Modelo Financiero'!$B$26*G7 -> 188.6 | H19: ='Modelo Financiero'!$B$26*H7 -> 200.1 | I19: ='Modelo Financiero'!$B$26*I7 -> 212.75 | ... M19: ='Modelo Financiero'!$B$26*M7 -> 265.65 | N19: =SUM(B19:M19) -> 2344.85
A20: OpenAI: GPT-4o-mini | B20: =(B4*'Modelo Financiero'!B13+B5*'Modelo Financiero'!B14+B6*'Modelo Financiero'!B15)*('Modelo Financiero'!B17*'Modelo Financiero'!B27+'Modelo Financiero'!B18*'Modelo Financiero'!B28)/1000000 -> 0.5184 | C20: =(C4*'Modelo Financiero'!B13+C5*'Modelo Financiero'!B14+C6*'Modelo Financiero'!B15)*('Modelo Financiero'!B17*'Modelo Financiero'!B27+'Modelo Financiero'!B18*'Modelo Financiero'!B28)/1000000 -> 0.6132 | D20: =(D4*'Modelo Financiero'!B13+D5*'Modelo Financiero'!B14+D6*'Modelo Financiero'!B15)*('Modelo Financiero'!B17*'Modelo Financiero'!B27+'Modelo Financiero'!B18*'Modelo Financiero'!B28)/1000000 -> 0.7272 | E20: =(E4*'Modelo Financiero'!B13+E5*'Modelo Financiero'!B14+E6*'Modelo Financiero'!B15)*('Modelo Financiero'!B17*'Modelo Financiero'!B27+'Modelo Financiero'!B18*'Modelo Financiero'!B28)/1000000 -> 0.8292 | F20: =(F4*'Modelo Financiero'!B13+F5*'Modelo Financiero'!B14+F6*'Modelo Financiero'!B15)*('Modelo Financiero'!B17*'Modelo Financiero'!B27+'Modelo Financiero'!B18*'Modelo Financiero'!B28)/1000000 -> 0.9312 | G20: =(G4*'Modelo Financiero'!B13+G5*'Modelo Financiero'!B14+G6*'Modelo Financiero'!B15)*('Modelo Financiero'!B17*'Modelo Financiero'!B27+'Modelo Financiero'!B18*'Modelo Financiero'!B28)/1000000 -> 1.0524 | H20: =(H4*'Modelo Financiero'!B13+H5*'Modelo Financiero'!B14+H6*'Modelo Financiero'!B15)*('Modelo Financiero'!B17*'Modelo Financiero'!B27+'Modelo Financiero'!B18*'Modelo Financiero'!B28)/1000000 -> 1.1616 | I20: =(I4*'Modelo Financiero'!B13+I5*'Modelo Financiero'!B14+I6*'Modelo Financiero'!B15)*('Modelo Financiero'!B17*'Modelo Financiero'!B27+'Modelo Financiero'!B18*'Modelo Financiero'!B28)/1000000 -> 1.2744 | J20: =(J4*'Modelo Financiero'!B13+J5*'Modelo Financiero'!B14+J6*'Modelo Financiero'!B15)*('Modelo Financiero'!B17*'Modelo Financiero'!B27+'Modelo Financiero'!B18*'Modelo Financiero'!B28)/1000000 -> 1.3872 | K20: =(K4*'Modelo Financiero'!B13+K5*'Modelo Financiero'!B14+K6*'Modelo Financiero'!B15)*('Modelo Financiero'!B17*'Modelo Financiero'!B27+'Modelo Financiero'!B18*'Modelo Financiero'!B28)/1000000 -> 1.5 | L20: =(L4*'Modelo Financiero'!B13+L5*'Modelo Financiero'!B14+L6*'Modelo Financiero'!B15)*('Modelo Financiero'!B17*'Modelo Financiero'!B27+'Modelo Financiero'!B18*'Modelo Financiero'!B28)/1000000 -> 1.632 | M20: =(M4*'Modelo Financiero'!B13+M5*'Modelo Financiero'!B14+M6*'Modelo Financiero'!B15)*('Modelo Financiero'!B17*'Modelo Financiero'!B27+'Modelo Financiero'!B18*'Modelo Financiero'!B28)/1000000 -> 1.764 | N20: =SUM(B20:M20) -> 13.3908
A21: Total Costos Variables | B21: =SUM(B17:B20) -> 196.8184 | C21: =SUM(C17:C20) -> 220.75695 | D21: =SUM(D17:D20) -> 248.3647 | E21: =SUM(E17:E20) -> 273.24795 | F21: =SUM(F17:F20) -> 298.1312 | G21: =SUM(G17:G20) -> 326.68365 | H21: =SUM(H17:H20) -> 352.5116 | I21: =SUM(I17:I20) -> 379.9619 | ... M21: =SUM(M17:M20) -> 497.1015 | N21: =SUM(B21:M21) -> 4101.8345
A23: COSTOS FIJOS
A24: Railway Hosting | B24: ='Modelo Financiero'!B30 -> 5 | C24: ='Modelo Financiero'!B30 -> 5 | D24: ='Modelo Financiero'!B30 -> 5 | E24: ='Modelo Financiero'!B30 -> 5 | F24: ='Modelo Financiero'!B30 -> 5 | G24: ='Modelo Financiero'!B30 -> 5 | H24: ='Modelo Financiero'!B30 -> 5 | I24: ='Modelo Financiero'!B30 -> 5 | J24: ='Modelo Financiero'!B30 -> 5 | K24: ='Modelo Financiero'!B30 -> 5 | L24: ='Modelo Financiero'!B30 -> 5 | M24: ='Modelo Financiero'!B30 -> 5 | N24: =SUM(B24:M24) -> 60
A25: Apple Developer Program | B25: ='Modelo Financiero'!B31 -> 8.25 | C25: ='Modelo Financiero'!B31 -> 8.25 | D25: ='Modelo Financiero'!B31 -> 8.25 | E25: ='Modelo Financiero'!B31 -> 8.25 | F25: ='Modelo Financiero'!B31 -> 8.25 | G25: ='Modelo Financiero'!B31 -> 8.25 | H25: ='Modelo Financiero'!B31 -> 8.25 | I25: ='Modelo Financiero'!B31 -> 8.25 | J25: ='Modelo Financiero'!B31 -> 8.25 | K25: ='Modelo Financiero'!B31 -> 8.25 | L25: ='Modelo Financiero'!B31 -> 8.25 | M25: ='Modelo Financiero'!B31 -> 8.25 | N25: =SUM(B25:M25) -> 99
A26: Total Costos Fijos | B26: =B24+B25 -> 13.25 | C26: =C24+C25 -> 13.25 | D26: =D24+D25 -> 13.25 | E26: =E24+E25 -> 13.25 | F26: =F24+F25 -> 13.25 | G26: =G24+G25 -> 13.25 | H26: =H24+H25 -> 13.25 | I26: =I24+I25 -> 13.25 | ... M26: =M24+M25 -> 13.25 | N26: =SUM(B26:M26) -> 159
A28: RESULTADO
A29: Costo Total | B29: =B21+B26 -> 210.0684 | C29: =C21+C26 -> 234.00695 | D29: =D21+D26 -> 261.6147 | E29: =E21+E26 -> 286.49795 | F29: =F21+F26 -> 311.3812 | G29: =G21+G26 -> 339.93365 | H29: =H21+H26 -> 365.7616 | I29: =I21+I26 -> 393.2119 | ... M29: =M21+M26 -> 510.3515 | N29: =SUM(B29:M29) -> 4260.8345
A30: Revenue Neto | B30: =B14 -> 59.398 | C30: =C14 -> 89.0885 | D30: =D14 -> 127.2705 | E30: =E14 -> 161.211 | F30: =F14 -> 195.1515 | G30: =G14 -> 237.5835 | H30: =H14 -> 275.774 | I30: =I14 -> 313.9645 | ... M30: =M14 -> 483.7095 | N30: =SUM(B30:M30) -> 3122.679
A31: UTILIDAD / PÉRDIDA | B31: =B30-B29 -> -150.6704 | C31: =C30-C29 -> -144.91845 | D31: =D30-D29 -> -134.3442 | E31: =E30-E29 -> -125.28695 | F31: =F30-F29 -> -116.2297 | G31: =G30-G29 -> -102.35015 | H31: =H30-H29 -> -89.9876 | I31: =I30-I29 -> -79.2474 | ... M31: =M30-M29 -> -26.642 | N31: =SUM(B31:M31) -> -1138.1555
A32: Margen (%) | B32: =IF(B30=0,0,B31/B30) -> -2.5366241 | C32: =IF(C30=0,0,C31/C30) -> -1.6266797 | D32: =IF(D30=0,0,D31/D30) -> -1.05558 | E32: =IF(E30=0,0,E31/E30) -> -0.7771613 | F32: =IF(F30=0,0,F31/F30) -> -0.59558702 | G32: =IF(G30=0,0,G31/G30) -> -0.43079654 | H32: =IF(H30=0,0,H31/H30) -> -0.32630922 | I32: =IF(I30=0,0,I31/I30) -> -0.25240879 | ... N32: =IF(N30=0,0,N31/N30) -> -0.36448048

Sheet Break-Even
A1: ANÁLISIS BREAK-EVEN
A3: Costos fijos mensuales | B3: ='Proyección 12 Meses'!B26 -> 13.25
A4: Usuarios Free mes 1 | B4: ='Proyección 12 Meses'!B4 -> 100
A5: Revenue promedio por usuario Pro | B5: 4.99
A6: Revenue promedio por usuario Premium | B6: 12.99
A7: Revenue neto por Pro (después Apple 15%) | B7: =B5*(1-0.15) -> 4.2415
A8: Revenue neto por Premium (después Apple 15%) | B8: =B6*(1-0.15) -> 11.0415
A10: Costo variable por llamada (estimado) | B10: =('Proyección 12 Meses'!B21-'Modelo Financiero'!B29)/(B4*15+B5*50+B6*80) -> 0.068784165 | C10: Excluye ElevenLabs fijo
A12: BREAK-EVEN: Suscriptores Pro necesarios | B12: =IF(B7=0,0,CEILING(B3/B7,1)) -> 4 | C12: solo para cubrir costos fijos
A14: BREAK-EVEN: Suscriptores Premium necesarios | B14: =IF(B8=0,0,CEILING(B3/B8,1)) -> 2 | C14: solo para cubrir costos fijos
A17: ESCENARIO MERCADOPAGO (sin Apple)
A18: Costos fijos/mes (sin Apple Dev) | B18: =5+5+30+0.83+1.15 -> 41.98 | C18: Railway+ElevenLabs+Contador+Dominio+Twilio
A19: Neto Pro (MP ~4.16%) | B19: =4.99*(1-0.0416) -> 4.782416
A20: Neto Premium (MP ~4.16%) | B20: =12.99*(1-0.0416) -> 12.449616
A21: Break-even solo Pro | B21: =ROUNDUP(B18/B19,0) -> 9 | C21: suscriptores Pro
A22: Break-even solo Premium | B22: =ROUNDUP(B18/B20,0) -> 4 | C22: suscriptores Premium
A24: AHORRO MP vs Apple (por 50 Pro + 10 Premium, anual)
A25: Ahorro anual USD | B25: =((4.99*0.15-4.99*0.0416)*50+(12.99*0.15-12.99*0.0416)*10)*12 -> 493.52352
