Workbook

Sheet Cuentas & Servicios
A1: Servicio | B1: Tipo | C1: Uso en FiltroLlamadas | D1: Modelo de Cobro | E1: Costo Base (USD/mes) | F1: Variable | G1: Credenciales / Env Var | H1: URL Consola | I1: Estado
A2: Twilio | B2: Telefonía + WhatsApp | C2: Voz entrante, TTS Polly, WhatsApp msgs | D2: Pay-per-use | E2: 0 | F2: ~$0.02/min voz + $0.005/msg WA + $1.15/num | G2: TWILIO_ACCOUNT_SID, TWILIO_AUTH_TOKEN, TWILIO_WHATSAPP_NUMBER | H2: https://console.twilio.com | I2: Activo
A3: OpenAI | B3: LLM (GPT-4o-mini) | C3: Conversación IA + análisis post-llamada | D3: Pay-per-token | E3: 0 | F3: $0.15/1M input + $0.60/1M output tokens | G3: OPENAI_API_KEY | H3: https://platform.openai.com | I3: Activo
A4: ElevenLabs | B4: TTS Premium | C4: Voces ultra-realistas (Pro/Premium) | D4: Suscripción + uso | E4: 5 | F4: $5/mes Starter (30K chars) o $0.18/1K chars | G4: ELEVENLABS_API_KEY, ELEVENLABS_VOICE_ID | H4: https://elevenlabs.io | I4: Activo
A5: Railway | B5: Hosting Backend | C5: FastAPI + PostgreSQL en producción | D5: Suscripción + uso | E5: 5 | F5: $5/mes Hobby (incluye $5 crédito uso) | G5: DATABASE_URL, BASE_URL | H5: https://railway.app/dashboard | I5: Activo
A6: Railway PostgreSQL | B6: Base de Datos | C6: Incluido en Railway (mismo proyecto) | D6: Incluido | E6: 0 | F6: Incluido en los $5 de Railway | G6: DATABASE_URL | H6: https://railway.app/dashboard | I6: Activo
A7: Google Cloud | B7: OAuth2 Calendar API | C7: Integración Google Calendar (Pro) | D7: Gratis | E7: 0 | F7: Gratis hasta millones de requests | G7: GOOGLE_CLIENT_ID, GOOGLE_CLIENT_SECRET | H7: https://console.cloud.google.com | I7: Activo
A8: Microsoft Azure AD | B8: OAuth2 Calendar API | C8: Integración Outlook Calendar (Pro) | D8: Gratis | E8: 0 | F8: Gratis tier básico | G8: OUTLOOK_CLIENT_ID, OUTLOOK_CLIENT_SECRET | H8: https://portal.azure.com | I8: Pendiente
A9: Apple Developer | B9: App Store | C9: Publicación iOS + In-App Purchases | D9: Anual | E9: 8.25 | F9: $99/año = $8.25/mes | G9: Apple Developer Account | H9: https://developer.apple.com | I9: Pendiente
A10: Apple App Store | B10: Comisión ventas | C10: 15% de cada suscripción (Small Business) | D10: % ventas | E10: 0 | F10: 15% de revenue (< $1M USD/año) | G10: N/A | H10: https://appstoreconnect.apple.com | I10: Pendiente
A11: GitHub | B11: Repositorio | C11: Código fuente del proyecto | D11: Gratis | E11: 0 | F11: Gratis (repo privado) | G11: N/A | H11: https://github.com | I11: Activo
A12: RevenueCat (recomendado) | B12: Gestión suscripciones | C12: Manejo IAP Apple/Google, analytics | D12: Gratis hasta $2.5K | E12: 0 | F12: Gratis < $2,500 MRR, luego 1% | G12: N/A | H12: https://revenuecat.com | I12: Pendiente
A13: TOTAL COSTO BASE MENSUAL | E13: =SUM(E2:E12) -> 18.25

Sheet Modelo Financiero
A1: SUPUESTOS DEL MODELO
A3: Supuestos de Usuarios
A4: Usuarios Free | B4: 100 | C4: Supuesto mes 1
A5: Usuarios Pro ($4.99/mes) | B5: 10 | C5: Supuesto mes 1
A6: Usuarios Premium ($12.99/mes) | B6: 2 | C6: Supuesto mes 1
A7: Crecimiento mensual usuarios | B7: 0.15 | C7: 15% mes a mes
A8: Conversión Free → Pro | B8: 0.08 | C8: 8% de free se convierten
A9: Conversión Pro → Premium | B9: 0.05 | C9: 5% de pro suben
A10: Churn mensual | B10: 0.04 | C10: 4% se van cada mes
A12: Supuestos de Uso por Usuario/Mes
A13: Llamadas promedio (Free) | B13: 15 | C13: de 30 max
A14: Llamadas promedio (Pro) | B14: 50 | C14: de 200 max
A15: Llamadas promedio (Premium) | B15: 80 | C15: ilimitado
A16: Duración promedio llamada (min) | B16: 2.5
A17: Tokens input promedio/llamada | B17: 800 | C17: prompt + conversación
A18: Tokens output promedio/llamada | B18: 200 | C18: respuesta IA
A19: Chars TTS ElevenLabs/llamada | B19: 150 | C19: solo Pro/Premium
A20: WhatsApp msgs/llamada | B20: 2 | C20: alerta + resumen
A22: Costos Unitarios
A23: Twilio: voz recibir (USD/min) | B23: 0.0085 | C23: Source: twilio.com/voice/pricing
A24: Twilio: voz hacer (USD/min) | B24: 0.014 | C24: Source: twilio.com/voice/pricing
A25: Twilio: WhatsApp (USD/msg) | B25: 0.005 | C25: Source: twilio.com/whatsapp/pricing
A26: Twilio: número teléfono (USD/mes) | B26: 1.15 | C26: Source: twilio.com/pricing
A27: OpenAI: input (USD/1M tokens) | B27: 0.15 | C27: Source: openai.com/api/pricing
A28: OpenAI: output (USD/1M tokens) | B28: 0.6 | C28: Source: openai.com/api/pricing
A29: ElevenLabs: suscripción (USD/mes) | B29: 5 | C29: Starter plan
A30: Railway: hosting (USD/mes) | B30: 5 | C30: Hobby plan
A31: Apple Developer (USD/mes) | B31: 8.25 | C31: $99/año prorrateado
A32: Apple comisión (%) | B32: 0.15 | C32: Small Business Program

Sheet Proyección 12 Meses
A1: PROYECCIÓN FINANCIERA 12 MESES
B2: Mes 1 | C2: Mes 2 | D2: Mes 3 | E2: Mes 4 | F2: Mes 5 | G2: Mes 6 | H2: Mes 7 | I2: Mes 8 | J2: Mes 9 | K2: Mes 10 | L2: Mes 11 | M2: Mes 12 | N2: TOTAL AÑO
A3: USUARIOS
A4: Usuarios Free | B4: ='Modelo Financiero'!B4 -> 100 | C4: =ROUND(B4*(1+'Modelo Financiero'!B7)-B4*'Modelo Financiero'!B8-B4*'Modelo Financiero'!B10,0) -> 103 | D4: =ROUND(C4*(1+'Modelo Financiero'!B7)-C4*'Modelo Financiero'!B8-C4*'Modelo Financiero'!B10,0) -> 106 | E4: =ROUND(D4*(1+'Modelo Financiero'!B7)-D4*'Modelo Financiero'!B8-D4*'Modelo Financiero'!B10,0) -> 109 | F4: =ROUND(E4*(1+'Modelo Financiero'!B7)-E4*'Modelo Financiero'!B8-E4*'Modelo Financiero'!B10,0) -> 112 | G4: =ROUND(F4*(1+'Modelo Financiero'!B7)-F4*'Modelo Financiero'!B8-F4*'Modelo Financiero'!B10,0) -> 115 | H4: =ROUND(G4*(1+'Modelo Financiero'!B7)-G4*'Modelo Financiero'!B8-G4*'Modelo Financiero'!B10,0) -> 118 | I4: =ROUND(H4*(1+'Modelo Financiero'!B7)-H4*'Modelo Financiero'!B8-H4*'Modelo Financiero'!B10,0) -> 122 | J4: =ROUND(I4*(1+'Modelo Financiero'!B7)-I4*'Modelo Financiero'!B8-I4*'Modelo Financiero'!B10,0) -> 126 | K4: =ROUND(J4*(1+'Modelo Financiero'!B7)-J4*'Modelo Financiero'!B8-J4*'Modelo Financiero'!B10,0) -> 130 | L4: =ROUND(K4*(1+'Modelo Financiero'!B7)-K4*'Modelo Financiero'!B8-K4*'Modelo Financiero'!B10,0) -> 134 | M4: =ROUND(L4*(1+'Modelo Financiero'!B7)-L4*'Modelo Financiero'!B8-L4*'Modelo Financiero'!B10,0) -> 138 | N4: =M4 -> 138
A5: Usuarios Pro | B5: ='Modelo Financiero'!B5 -> 10 | C5: =ROUND(B5+B4*'Modelo Financiero'!B8-B5*'Modelo Financiero'!B9-B5*'Modelo Financiero'!B10,0) -> 17 | D5: =ROUND(C5+C4*'Modelo Financiero'!B8-C5*'Modelo Financiero'!B9-C5*'Modelo Financiero'!B10,0) -> 24 | E5: =ROUND(D5+D4*'Modelo Financiero'!B8-D5*'Modelo Financiero'!B9-D5*'Modelo Financiero'!B10,0) -> 30 | F5: =ROUND(E5+E4*'Modelo Financiero'!B8-E5*'Modelo Financiero'!B9-E5*'Modelo Financiero'!B10,0) -> 36 | G5: =ROUND(F5+F4*'Modelo Financiero'!B8-F5*'Modelo Financiero'!B9-F5*'Modelo Financiero'!B10,0) -> 42 | H5: =ROUND(G5+G4*'Modelo Financiero'!B8-G5*'Modelo Financiero'!B9-G5*'Modelo Financiero'!B10,0) -> 47 | I5: =ROUND(H5+H4*'Modelo Financiero'!B8-H5*'Modelo Financiero'!B9-H5*'Modelo Financiero'!B10,0) -> 52 | J5: =ROUND(I5+I4*'Modelo Financiero'!B8-I5*'Modelo Financiero'!B9-I5*'Modelo Financiero'!B10,0) -> 57 | K5: =ROUND(J5+J4*'Modelo Financiero'!B8-J5*'Modelo Financiero'!B9-J5*'Modelo Financiero'!B10,0) -> 62 | L5: =ROUND(K5+K4*'Modelo Financiero'!B8-K5*'Modelo Financiero'!B9-K5*'Modelo Financiero'!B10,0) -> 67 | M5: =ROUND(L5+L4*'Modelo Financiero'!B8-L5*'Modelo Financiero'!B9-L5*'Modelo Financiero'!B10,0) -> 72 | N5: =M5 -> 72
A6: Usuarios Premium | B6: ='Modelo Financiero'!B6 -> 2 | C6: =ROUND(B6+B5*'Modelo Financiero'!B9-B6*'Modelo Financiero'!B10,0) -> 2 | D6: =ROUND(C6+C5*'Modelo Financiero'!B9-C6*'Modelo Financiero'!B10,0) -> 3 | E6: =ROUND(D6+D5*'Modelo Financiero'!B9-D6*'Modelo Financiero'!B10,0) -> 4 | F6: =ROUND(E6+E5*'Modelo Financiero'!B9-E6*'Modelo Financiero'!B10,0) -> 5 | G6: =ROUND(F6+F5*'Modelo Financiero'!B9-F6*'Modelo Financiero'!B10,0) -> 7 | H6: =ROUND(G6+G5*'Modelo Financiero'!B9-G6*'Modelo Financiero'!B10,0) -> 9 | I6: =ROUND(H6+H5*'Modelo Financiero'!B9-H6*'Modelo Financiero'!B10,0) -> 11 | J6: =ROUND(I6+I5*'Modelo Financiero'!B9-I6*'Modelo Financiero'!B10,0) -> 13 | K6: =ROUND(J6+J5*'Modelo Financiero'!B9-J6*'Modelo Financiero'!B10,0) -> 15 | L6: =ROUND(K6+K5*'Modelo Financiero'!B9-K6*'Modelo Financiero'!B10,0) -> 18 | M6: =ROUND(L6+L5*'Modelo Financiero'!B9-L6*'Modelo Financiero'!B10,0) -> 21 | N6: =M6 -> 21
A7: Total Usuarios | B7: =B4+B5+B6 -> 112 | C7: =C4+C5+C6 -> 122 | D7: =D4+D5+D6 -> 133 | E7: =E4+E5+E6 -> 143 | F7: =F4+F5+F6 -> 153 | G7: =G4+G5+G6 -> 164 | H7: =H4+H5+H6 -> 174 | I7: =I4+I5+I6 -> 185 | ... M7: =M4+M5+M6 -> 231 | N7: =M7 -> 231
A9: REVENUE (antes de Apple)
A10: Revenue Pro (bruto) | B10: =B5*4.99 -> 49.9 | C10: =C5*4.99 -> 84.83 | D10: =D5*4.99 -> 119.76 | E10: =E5*4.99 -> 149.7 | F10: =F5*4.99 -> 179.64 | G10: =G5*4.99 -> 209.58 | H10: =H5*4.99 -> 234.53 | I10: =I5*4.99 -> 259.48 | ... M10: =M5*4.99 -> 359.28 | N10: =SUM(B10:M10) -> 2574.84
A11: Revenue Premium (bruto) | B11: =B6*12.99 -> 25.98 | C11: =C6*12.99 -> 25.98 | D11: =D6*12.99 -> 38.97 | E11: =E6*12.99 -> 51.96 | F11: =F6*12.99 -> 64.95 | G11: =G6*12.99 -> 90.93 | H11: =H6*12.99 -> 116.91 | I11: =I6*12.99 -> 142.89 | ... M11: =M6*12.99 -> 272.79 | N11: =SUM(B11:M11) -> 1428.9
A12: Revenue Bruto Total | B12: =B10+B11 -> 75.88 | C12: =C10+C11 -> 110.81 | D12: =D10+D11 -> 158.73 | E12: =E10+E11 -> 201.66 | F12: =F10+F11 -> 244.59 | G12: =G10+G11 -> 300.51 | H12: =H10+H11 -> 351.44 | I12: =I10+I11 -> 402.37 | ... M12: =M10+M11 -> 632.07 | N12: =SUM(B12:M12) -> 4003.74
A13: Comisión Apple (15%) | B13: =B12*'Modelo Financiero'!B32 -> 11.382 | C13: =C12*'Modelo Financiero'!B32 -> 16.6215 | D13: =D12*'Modelo Financiero'!B32 -> 23.8095 | E13: =E12*'Modelo Financiero'!B32 -> 30.249 | F13: =F12*'Modelo Financiero'!B32 -> 36.6885 | G13: =G12*'Modelo Financiero'!B32 -> 45.0765 | H13: =H12*'Modelo Financiero'!B32 -> 52.716 | I13: =I12*'Modelo Financiero'!B32 -> 60.3555 | J13: =J12*'Modelo Financiero'!B32 -> 67.995 | K13: =K12*'Modelo Financiero'!B32 -> 75.6345 | L13: =L12*'Modelo Financiero'!B32 -> 85.2225 | M13: =M12*'Modelo Financiero'!B32 -> 94.8105 | N13: =SUM(B13:M13) -> 600.561
A14: Revenue Neto | B14: =B12-B13 -> 64.498 | C14: =C12-C13 -> 94.1885 | D14: =D12-D13 -> 134.9205 | E14: =E12-E13 -> 171.411 | F14: =F12-F13 -> 207.9015 | G14: =G12-G13 -> 255.4335 | H14: =H12-H13 -> 298.724 | I14: =I12-I13 -> 342.0145 | ... M14: =M12-M13 -> 537.2595 | N14: =SUM(B14:M14) -> 3403.179
A16: COSTOS VARIABLES
A17: Twilio: Voz (llamadas) | B17: =(B4*'Modelo Financiero'!B13+B5*'Modelo Financiero'!B14+B6*'Modelo Financiero'!B15)*'Modelo Financiero'!B16*'Modelo Financiero'!B23 -> 45.9 | C17: =(C4*'Modelo Financiero'!B13+C5*'Modelo Financiero'!B14+C6*'Modelo Financiero'!B15)*'Modelo Financiero'!B16*'Modelo Financiero'!B23 -> 54.29375 | D17: =(D4*'Modelo Financiero'!B13+D5*'Modelo Financiero'!B14+D6*'Modelo Financiero'!B15)*'Modelo Financiero'!B16*'Modelo Financiero'!B23 -> 64.3875 | E17: =(E4*'Modelo Financiero'!B13+E5*'Modelo Financiero'!B14+E6*'Modelo Financiero'!B15)*'Modelo Financiero'!B16*'Modelo Financiero'!B23 -> 73.41875 | F17: =(F4*'Modelo Financiero'!B13+F5*'Modelo Financiero'!B14+F6*'Modelo Financiero'!B15)*'Modelo Financiero'!B16*'Modelo Financiero'!B23 -> 82.45 | G17: =(G4*'Modelo Financiero'!B13+G5*'Modelo Financiero'!B14+G6*'Modelo Financiero'!B15)*'Modelo Financiero'!B16*'Modelo Financiero'!B23 -> 93.18125 | H17: =(H4*'Modelo Financiero'!B13+H5*'Modelo Financiero'!B14+H6*'Modelo Financiero'!B15)*'Modelo Financiero'!B16*'Modelo Financiero'!B23 -> 102.85 | I17: =(I4*'Modelo Financiero'!B13+I5*'Modelo Financiero'!B14+I6*'Modelo Financiero'!B15)*'Modelo Financiero'!B16*'Modelo Financiero'!B23 -> 112.8375 | J17: =(J4*'Modelo Financiero'!B13+J5*'Modelo Financiero'!B14+J6*'Modelo Financiero'!B15)*'Modelo Financiero'!B16*'Modelo Financiero'!B23 -> 122.825 | K17: =(K4*'Modelo Financiero'!B13+K5*'Modelo Financiero'!B14+K6*'Modelo Financiero'!B15)*'Modelo Financiero'!B16*'Modelo Financiero'!B23 -> 132.8125 | L17: =(L4*'Modelo Financiero'!B13+L5*'Modelo Financiero'!B14+L6*'Modelo Financiero'!B15)*'Modelo Financiero'!B16*'Modelo Financiero'!B23 -> 144.5 | M17: =(M4*'Modelo Financiero'!B13+M5*'Modelo Financiero'!B14+M6*'Modelo Financiero'!B15)*'Modelo Financiero'!B16*'Modelo Financiero'!B23 -> 156.1875 | N17: =SUM(B17:M17) -> 1185.6437
A18: Twilio: WhatsApp | B18: =(B4*'Modelo Financiero'!B13+B5*'Modelo Financiero'!B14+B6*'Modelo Financiero'!B15)*'Modelo Financiero'!B20*'Modelo Financiero'!B25 -> 21.6 | C18: =(C4*'Modelo Financiero'!B13+C5*'Modelo Financiero'!B14+C6*'Modelo Financiero'!B15)*'Modelo Financiero'!B20*'Modelo Financiero'!B25 -> 25.55 | D18: =(D4*'Modelo Financiero'!B13+D5*'Modelo Financiero'!B14+D6*'Modelo Financiero'!B15)*'Modelo Financiero'!B20*'Modelo Financiero'!B25 -> 30.3 | E18: =(E4*'Modelo Financiero'!B13+E5*'Modelo Financiero'!B14+E6*'Modelo Financiero'!B15)*'Modelo Financiero'!B20*'Modelo Financiero'!B25 -> 34.55 | F18: =(F4*'Modelo Financiero'!B13+F5*'Modelo Financiero'!B14+F6*'Modelo Financiero'!B15)*'Modelo Financiero'!B20*'Modelo Financiero'!B25 -> 38.8 | G18: =(G4*'Modelo Financiero'!B13+G5*'Modelo Financiero'!B14+G6*'Modelo Financiero'!B15)*'Modelo Financiero'!B20*'Modelo Financiero'!B25 -> 43.85 | H18: =(H4*'Modelo Financiero'!B13+H5*'Modelo Financiero'!B14+H6*'Modelo Financiero'!B15)*'Modelo Financiero'!B20*'Modelo Financiero'!B25 -> 48.4 | I18: =(I4*'Modelo Financiero'!B13+I5*'Modelo Financiero'!B14+I6*'Modelo Financiero'!B15)*'Modelo Financiero'!B20*'Modelo Financiero'!B25 -> 53.1 | J18: =(J4*'Modelo Financiero'!B13+J5*'Modelo Financiero'!B14+J6*'Modelo Financiero'!B15)*'Modelo Financiero'!B20*'Modelo Financiero'!B25 -> 57.8 | K18: =(K4*'Modelo Financiero'!B13+K5*'Modelo Financiero'!B14+K6*'Modelo Financiero'!B15)*'Modelo Financiero'!B20*'Modelo Financiero'!B25 -> 62.5 | L18: =(L4*'Modelo Financiero'!B13+L5*'Modelo Financiero'!B14+L6*'Modelo Financiero'!B15)*'Modelo Financiero'!B20*'Modelo Financiero'!B25 -> 68 | M18: =(M4*'Modelo Financiero'!B13+M5*'Modelo Financiero'!B14+M6*'Modelo Financiero'!B15)*'Modelo Financiero'!B20*'Modelo Financiero'!B25 -> 73.5 | N18: =SUM(B18:M18) -> 557.95
A19: Twilio: Números telefónicos | B19: ='Modelo Financiero'!B26 -> 1.15 | C19: ='Modelo Financiero'!B26 -> 1.15 | D19: ='Modelo Financiero'!B26 -> 1.15 | E19: ='Modelo Financiero'!B26 -> 1.15 | F19: ='Modelo Financiero'!B26 -> 1.15 | G19: ='Modelo Financiero'!B26 -> 1.15 | H19: ='Modelo Financiero'!B26 -> 1.15 | I19: ='Modelo Financiero'!B26 -> 1.15 | J19: ='Modelo Financiero'!B26 -> 1.15 | K19: ='Modelo Financiero'!B26 -> 1.15 | L19: ='Modelo Financiero'!B26 -> 1.15 | M19: ='Modelo Financiero'!B26 -> 1.15 | N19: =SUM(B19:M19) -> 13.8
A20: OpenAI: GPT-4o-mini | B20: =(B4*'Modelo Financiero'!B13+B5*'Modelo Financiero'!B14+B6*'Modelo Financiero'!B15)*('Modelo Financiero'!B17*'Modelo Financiero'!B27+'Modelo Financiero'!B18*'Modelo Financiero'!B28)/1000000 -> 0.5184 | C20: =(C4*'Modelo Financiero'!B13+C5*'Modelo Financiero'!B14+C6*'Modelo Financiero'!B15)*('Modelo Financiero'!B17*'Modelo Financiero'!B27+'Modelo Financiero'!B18*'Modelo Financiero'!B28)/1000000 -> 0.6132 | D20: =(D4*'Modelo Financiero'!B13+D5*'Modelo Financiero'!B14+D6*'Modelo Financiero'!B15)*('Modelo Financiero'!B17*'Modelo Financiero'!B27+'Modelo Financiero'!B18*'Modelo Financiero'!B28)/1000000 -> 0.7272 | E20: =(E4*'Modelo Financiero'!B13+E5*'Modelo Financiero'!B14+E6*'Modelo Financiero'!B15)*('Modelo Financiero'!B17*'Modelo Financiero'!B27+'Modelo Financiero'!B18*'Modelo Financiero'!B28)/1000000 -> 0.8292 | F20: =(F4*'Modelo Financiero'!B13+F5*'Modelo Financiero'!B14+F6*'Modelo Financiero'!B15)*('Modelo Financiero'!B17*'Modelo Financiero'!B27+'Modelo Financiero'!B18*'Modelo Financiero'!B28)/1000000 -> 0.9312 | G20: =(G4*'Modelo Financiero'!B13+G5*'Modelo Financiero'!B14+G6*'Modelo Financiero'!B15)*('Modelo Financiero'!B17*'Modelo Financiero'!B27+'Modelo Financiero'!B18*'Modelo Financiero'!B28)/1000000 -> 1.0524 | H20: =(H4*'Modelo Financiero'!B13+H5*'Modelo Financiero'!B14+H6*'Modelo Financiero'!B15)*('Modelo Financiero'!B17*'Modelo Financiero'!B27+'Modelo Financiero'!B18*'Modelo Financiero'!B28)/1000000 -> 1.1616 | I20: =(I4*'Modelo Financiero'!B13+I5*'Modelo Financiero'!B14+I6*'Modelo Financiero'!B15)*('Modelo Financiero'!B17*'Modelo Financiero'!B27+'Modelo Financiero'!B18*'Modelo Financiero'!B28)/1000000 -> 1.2744 | J20: =(J4*'Modelo Financiero'!B13+J5*'Modelo Financiero'!B14+J6*'Modelo Financiero'!B15)*('Modelo Financiero'!B17*'Modelo Financiero'!B27+'Modelo Financiero'!B18*'Modelo Financiero'!B28)/1000000 -> 1.3872 | K20: =(K4*'Modelo Financiero'!B13+K5*'Modelo Financiero'!B14+K6*'Modelo Financiero'!B15)*('Modelo Financiero'!B17*'Modelo Financiero'!B27+'Modelo Financiero'!B18*'Modelo Financiero'!B28)/1000000 -> 1.5 | L20: =(L4*'Modelo Financiero'!B13+L5*'Modelo Financiero'!B14+L6*'Modelo Financiero'!B15)*('Modelo Financiero'!B17*'Modelo Financiero'!B27+'Modelo Financiero'!B18*'Modelo Financiero'!B28)/1000000 -> 1.632 | M20: =(M4*'Modelo Financiero'!B13+M5*'Modelo Financiero'!B14+M6*'Modelo Financiero'!B15)*('Modelo Financiero'!B17*'Modelo Financiero'!B27+'Modelo Financiero'!B18*'Modelo Financiero'!B28)/1000000 -> 1.764 | N20: =SUM(B20:M20) -> 13.3908
A21: ElevenLabs: TTS | B21: ='Modelo Financiero'!B29 -> 5 | C21: ='Modelo Financiero'!B29 -> 5 | D21: ='Modelo Financiero'!B29 -> 5 | E21: ='Modelo Financiero'!B29 -> 5 | F21: ='Modelo Financiero'!B29 -> 5 | G21: ='Modelo Financiero'!B29 -> 5 | H21: ='Modelo Financiero'!B29 -> 5 | I21: ='Modelo Financiero'!B29 -> 5 | J21: ='Modelo Financiero'!B29 -> 5 | K21: ='Modelo Financiero'!B29 -> 5 | L21: ='Modelo Financiero'!B29 -> 5 | M21: ='Modelo Financiero'!B29 -> 5 | N21: =SUM(B21:M21) -> 60
A22: Total Costos Variables | B22: =SUM(B17:B21) -> 74.1684 | C22: =SUM(C17:C21) -> 86.60695 | D22: =SUM(D17:D21) -> 101.5647 | E22: =SUM(E17:E21) -> 114.94795 | F22: =SUM(F17:F21) -> 128.3312 | G22: =SUM(G17:G21) -> 144.23365 | H22: =SUM(H17:H21) -> 158.5616 | I22: =SUM(I17:I21) -> 173.3619 | ... M22: =SUM(M17:M21) -> 237.6015 | N22: =SUM(B22:M22) -> 1830.7846
A24: COSTOS FIJOS
A25: Railway Hosting | B25: ='Modelo Financiero'!B30 -> 5 | C25: ='Modelo Financiero'!B30 -> 5 | D25: ='Modelo Financiero'!B30 -> 5 | E25: ='Modelo Financiero'!B30 -> 5 | F25: ='Modelo Financiero'!B30 -> 5 | G25: ='Modelo Financiero'!B30 -> 5 | H25: ='Modelo Financiero'!B30 -> 5 | I25: ='Modelo Financiero'!B30 -> 5 | J25: ='Modelo Financiero'!B30 -> 5 | K25: ='Modelo Financiero'!B30 -> 5 | L25: ='Modelo Financiero'!B30 -> 5 | M25: ='Modelo Financiero'!B30 -> 5 | N25: =SUM(B25:M25) -> 60
A26: Apple Developer Program | B26: ='Modelo Financiero'!B31 -> 8.25 | C26: ='Modelo Financiero'!B31 -> 8.25 | D26: ='Modelo Financiero'!B31 -> 8.25 | E26: ='Modelo Financiero'!B31 -> 8.25 | F26: ='Modelo Financiero'!B31 -> 8.25 | G26: ='Modelo Financiero'!B31 -> 8.25 | H26: ='Modelo Financiero'!B31 -> 8.25 | I26: ='Modelo Financiero'!B31 -> 8.25 | J26: ='Modelo Financiero'!B31 -> 8.25 | K26: ='Modelo Financiero'!B31 -> 8.25 | L26: ='Modelo Financiero'!B31 -> 8.25 | M26: ='Modelo Financiero'!B31 -> 8.25 | N26: =SUM(B26:M26) -> 99
A27: Total Costos Fijos | B27: =B25+B26 -> 13.25 | C27: =C25+C26 -> 13.25 | D27: =D25+D26 -> 13.25 | E27: =E25+E26 -> 13.25 | F27: =F25+F26 -> 13.25 | G27: =G25+G26 -> 13.25 | H27: =H25+H26 -> 13.25 | I27: =I25+I26 -> 13.25 | ... M27: =M25+M26 -> 13.25 | N27: =SUM(B27:M27) -> 159
A29: RESULTADO
A30: Costo Total | B30: =B22+B27 -> 87.4184 | C30: =C22+C27 -> 99.85695 | D30: =D22+D27 -> 114.8147 | E30: =E22+E27 -> 128.19795 | F30: =F22+F27 -> 141.5812 | G30: =G22+G27 -> 157.48365 | H30: =H22+H27 -> 171.8116 | I30: =I22+I27 -> 186.6119 | ... M30: =M22+M27 -> 250.8515 | N30: =SUM(B30:M30) -> 1989.7846
A31: Revenue Neto | B31: =B14 -> 64.498 | C31: =C14 -> 94.1885 | D31: =D14 -> 134.9205 | E31: =E14 -> 171.411 | F31: =F14 -> 207.9015 | G31: =G14 -> 255.4335 | H31: =H14 -> 298.724 | I31: =I14 -> 342.0145 | ... M31: =M14 -> 537.2595 | N31: =SUM(B31:M31) -> 3403.179
A32: UTILIDAD / PÉRDIDA | B32: =B31-B30 -> -22.9204 | C32: =C31-C30 -> -5.66845 | D32: =D31-D30 -> 20.1058 | E32: =E31-E30 -> 43.21305 | F32: =F31-F30 -> 66.3203 | G32: =G31-G30 -> 97.94985 | H32: =H31-H30 -> 126.9124 | I32: =I31-I30 -> 155.4026 | ... M32: =M31-M30 -> 286.408 | N32: =SUM(B32:M32) -> 1413.3945
A33: Margen (%) | B33: =IF(B31=0,0,B32/B31) -> -0.35536606 | C33: =IF(C31=0,0,C32/C31) -> -0.060181976 | D33: =IF(D31=0,0,D32/D31) -> 0.14901961 | E33: =IF(E31=0,0,E32/E31) -> 0.25210197 | F33: =IF(F31=0,0,F32/F31) -> 0.31899866 | G33: =IF(G31=0,0,G32/G31) -> 0.38346517 | H33: =IF(H31=0,0,H32/H31) -> 0.42484836 | I33: =IF(I31=0,0,I32/I31) -> 0.4543743 | ... N33: =IF(N31=0,0,N32/N31) -> 0.41531593

Sheet Break-Even
A1: ANÁLISIS BREAK-EVEN
A3: Costos fijos mensuales | B3: ='Proyección 12 Meses'!B27 -> 13.25
A4: Usuarios Free mes 1 | B4: ='Proyección 12 Meses'!B4 -> 100
A5: Revenue promedio por usuario Pro | B5: 4.99
A6: Revenue promedio por usuario Premium | B6: 12.99
A7: Revenue neto por Pro (después Apple 15%) | B7: =B5*(1-0.15) -> 4.2415
A8: Revenue neto por Premium (después Apple 15%) | B8: =B6*(1-0.15) -> 11.0415
A10: Costo variable por llamada (estimado) | B10: =('Proyección 12 Meses'!B22-'Modelo Financiero'!B29)/(B4*15+B5*50+B6*80) -> 0.024803098 | C10: Excluye ElevenLabs fijo
A12: BREAK-EVEN: Suscriptores Pro necesarios | B12: =IF(B7=0,0,CEILING(B3/B7,1)) -> 4 | C12: solo para cubrir costos fijos
A14: BREAK-EVEN: Suscriptores Premium necesarios | B14: =IF(B8=0,0,CEILING(B3/B8,1)) -> 2 | C14: solo para cubrir costos fijos
